Bio/File.py
Bio/LogisticRegression.py
Bio/MarkovModel.py
Bio/MaxEntropy.py
Bio/NaiveBayes.py
Bio/Seq.py
Bio/SeqFeature.py
Bio/SeqRecord.py
Bio/__init__.py
Bio/_utils.py
Bio/bgzf.py
Bio/cpairwise2.cpython-39-darwin.so
Bio/cpairwise2module.c
Bio/kNN.py
Bio/pairwise2.py
Bio/Affy/CelFile.py
Bio/Affy/__init__.py
Bio/Align/AlignInfo.py
Bio/Align/__init__.py
Bio/Align/_aligners.c
Bio/Align/_aligners.cpython-39-darwin.so
Bio/Align/bed.py
Bio/Align/clustal.py
Bio/Align/emboss.py
Bio/Align/fasta_m8.py
Bio/Align/interfaces.py
Bio/Align/maf.py
Bio/Align/mauve.py
Bio/Align/msf.py
Bio/Align/nexus.py
Bio/Align/phylip.py
Bio/Align/psl.py
Bio/Align/stockholm.py
Bio/Align/Applications/_ClustalOmega.py
Bio/Align/Applications/_Clustalw.py
Bio/Align/Applications/_Dialign.py
Bio/Align/Applications/_MSAProbs.py
Bio/Align/Applications/_Mafft.py
Bio/Align/Applications/_Muscle.py
Bio/Align/Applications/_Prank.py
Bio/Align/Applications/_Probcons.py
Bio/Align/Applications/_TCoffee.py
Bio/Align/Applications/__init__.py
Bio/Align/substitution_matrices/__init__.py
Bio/Align/substitution_matrices/data/BENNER22
Bio/Align/substitution_matrices/data/BENNER6
Bio/Align/substitution_matrices/data/BENNER74
Bio/Align/substitution_matrices/data/BLOSUM45
Bio/Align/substitution_matrices/data/BLOSUM50
Bio/Align/substitution_matrices/data/BLOSUM62
Bio/Align/substitution_matrices/data/BLOSUM80
Bio/Align/substitution_matrices/data/BLOSUM90
Bio/Align/substitution_matrices/data/DAYHOFF
Bio/Align/substitution_matrices/data/FENG
Bio/Align/substitution_matrices/data/GENETIC
Bio/Align/substitution_matrices/data/GONNET1992
Bio/Align/substitution_matrices/data/HOXD70
Bio/Align/substitution_matrices/data/JOHNSON
Bio/Align/substitution_matrices/data/JONES
Bio/Align/substitution_matrices/data/LEVIN
Bio/Align/substitution_matrices/data/MCLACHLAN
Bio/Align/substitution_matrices/data/MDM78
Bio/Align/substitution_matrices/data/NUC.4.4
Bio/Align/substitution_matrices/data/PAM250
Bio/Align/substitution_matrices/data/PAM30
mah51_biopython-1.1.dist-info/LICENSE
mah51_biopython-1.1.dist-info/LICENSE.rst
mah51_biopython-1.1.dist-info/METADATA
mah51_biopython-1.1.dist-info/WHEEL
mah51_biopython-1.1.dist-info/top_level.txt
mah51_biopython-1.1.dist-info/RECORD
