Metadata-Version: 2.1
Name: mah51-biopython
Version: 1.1
Summary: Freely available tools for computational molecular biology.
Home-page: https://biopython.org/
Author: The Biopython Contributors
Author-email: biopython@biopython.org
Project-URL: Documentation, https://biopython.org/wiki/Documentation
Project-URL: Source, https://github.com/biopython/biopython/
Project-URL: Tracker, https://github.com/biopython/biopython/issues
Classifier: Development Status :: 5 - Production/Stable
Classifier: Intended Audience :: Developers
Classifier: Intended Audience :: Science/Research
Classifier: License :: Freely Distributable
Classifier: Operating System :: OS Independent
Classifier: Programming Language :: Python
Classifier: Programming Language :: Python :: 3
Classifier: Programming Language :: Python :: 3.7
Classifier: Programming Language :: Python :: 3.8
Classifier: Programming Language :: Python :: 3.9
Classifier: Programming Language :: Python :: 3.10
Classifier: Topic :: Scientific/Engineering
Classifier: Topic :: Scientific/Engineering :: Bio-Informatics
Classifier: Topic :: Software Development :: Libraries :: Python Modules
Requires-Python: >=3.7
License-File: LICENSE
License-File: LICENSE.rst
Requires-Dist: numpy
